commonutil_jsonstdioipc/__init__.py
commonutil_jsonstdioipc/py.typed
commonutil_jsonstdioipc-3.0.3.dist-info/METADATA
commonutil_jsonstdioipc-3.0.3.dist-info/WHEEL
commonutil_jsonstdioipc-3.0.3.dist-info/top_level.txt
commonutil_jsonstdioipc-3.0.3.dist-info/RECORD
